{
    "interact": {
        "magic": "APF_VER_1",
        "variables": [
            {
                "name": "Reset Core",
                "id": 1,
                "type": "action",
                "enabled": true,
                "address": "0xF0000000",
                "value": 1
            },
            {
                "name": "DIP",
                "id": 1000,
                "type": "number_u32",
                "enabled": false,
                "address": "0xF1000000"
            },
            {
                "name": "Coinage",
                "port": "DSW1",
                "id": 2,
                "type": "list",
                "enabled": true,
                "persist": true,
                "address": "0xF1000000",
                "defaultval": 2,
                "mask": "0xFFFFFFF8",
                "options": [
                    {
                        "name": "3 Coins/1 Credit",
                        "value": "0x0002"
                    },
                    {
                        "name": "2 Coins/1 Credit",
                        "value": "0x0004"
                    },
                    {
                        "name": "1 Coin/1 Credit",
                        "value": "0x0007"
                    },
                    {
                        "name": "2 Coins/3 Credits",
                        "value": "0x0003"
                    },
                    {
                        "name": "1 Coin/2 Credits",
                        "value": "0x0006"
                    },
                    {
                        "name": "1 Coin/3 Credits",
                        "value": "0x0005"
                    },
                    {
                        "name": "Free Play",
                        "value": "0x0000"
                    }
                ]
            },
            {
                "name": "Demo Sounds",
                "port": "DSW1",
                "id": 3,
                "type": "list",
                "enabled": true,
                "persist": true,
                "address": "0xF1000000",
                "defaultval": 1,
                "mask": "0xFFFFFFF7",
                "options": [
                    {
                        "name": "Off",
                        "value": "0x0000"
                    },
                    {
                        "name": "On",
                        "value": "0x0008"
                    }
                ]
            },
            {
                "name": "Cabinet",
                "port": "DSW1",
                "id": 4,
                "type": "list",
                "enabled": true,
                "persist": true,
                "address": "0xF1000000",
                "defaultval": 0,
                "mask": "0xFFFFFFEF",
                "options": [
                    {
                        "name": "Upright",
                        "value": "0x0000"
                    },
                    {
                        "name": "Cocktail",
                        "value": "0x0010"
                    }
                ]
            },
            {
                "name": "Intermissions",
                "port": "DSW1",
                "id": 5,
                "type": "list",
                "enabled": true,
                "persist": true,
                "address": "0xF1000000",
                "defaultval": 0,
                "mask": "0xFFFFFFDF",
                "options": [
                    {
                        "name": "Off",
                        "value": "0x0020"
                    },
                    {
                        "name": "On",
                        "value": "0x0000"
                    }
                ]
            },
            {
                "name": "Service Mode",
                "port": "DSW1",
                "id": 6,
                "type": "list",
                "enabled": true,
                "persist": true,
                "address": "0xF1000000",
                "defaultval": 0,
                "mask": "0xFFFFFFBF",
                "options": [
                    {
                        "name": "Off",
                        "value": "0x0040"
                    },
                    {
                        "name": "On",
                        "value": "0x0000"
                    }
                ]
            },
            {
                "name": "Lives",
                "port": "DSW2",
                "id": 7,
                "type": "list",
                "enabled": true,
                "persist": true,
                "address": "0xF1000000",
                "defaultval": 2,
                "mask": "0xFFFFFCFF",
                "options": [
                    {
                        "name": "1",
                        "value": "0x0100"
                    },
                    {
                        "name": "2",
                        "value": "0x0000"
                    },
                    {
                        "name": "3",
                        "value": "0x0300"
                    },
                    {
                        "name": "5",
                        "value": "0x0200"
                    }
                ]
            },
            {
                "name": "Difficulty",
                "port": "DSW2",
                "id": 8,
                "type": "list",
                "enabled": true,
                "persist": true,
                "address": "0xF1000000",
                "defaultval": 2,
                "mask": "0xFFFFF3FF",
                "options": [
                    {
                        "name": "Easy",
                        "value": "0x0C00"
                    },
                    {
                        "name": "Medium",
                        "value": "0x0800"
                    },
                    {
                        "name": "Hard",
                        "value": "0x0400"
                    },
                    {
                        "name": "Hardest",
                        "value": "0x0000"
                    }
                ]
            },
            {
                "name": "Bonus Life",
                "port": "DSW2",
                "id": 9,
                "type": "list",
                "enabled": true,
                "persist": true,
                "address": "0xF1000000",
                "defaultval": 4,
                "mask": "0xFFFF0FFF",
                "options": [
                    {
                        "name": "20k, 120k, then every 100k",
                        "value": "0xB000"
                    },
                    {
                        "name": "40k, 120k, then every 100k",
                        "value": "0xA000"
                    },
                    {
                        "name": "60k, 160k, then every 100k",
                        "value": "0x9000"
                    },
                    {
                        "name": "Every 100k",
                        "value": "0x8000"
                    },
                    {
                        "name": "20k, 220k, then every 200k",
                        "value": "0x7000"
                    },
                    {
                        "name": "40k, 240k, then every 200k",
                        "value": "0x6000"
                    },
                    {
                        "name": "60k, 260k, then every 200k",
                        "value": "0x5000"
                    },
                    {
                        "name": "Every 200k",
                        "value": "0x4000"
                    },
                    {
                        "name": "20k, 320k, then every 300k",
                        "value": "0x3000"
                    },
                    {
                        "name": "40k, 340k, then every 300k",
                        "value": "0x2000"
                    },
                    {
                        "name": "60k, 360k, then every 300k",
                        "value": "0x1000"
                    },
                    {
                        "name": "Every 300k",
                        "value": "0x0000"
                    },
                    {
                        "name": "20k only",
                        "value": "0xF000"
                    },
                    {
                        "name": "40k only",
                        "value": "0xE000"
                    },
                    {
                        "name": "60k only",
                        "value": "0xD000"
                    },
                    {
                        "name": "None",
                        "value": "0xC000"
                    }
                ]
            }
        ],
        "messages": []
    }
}